RequestsCommon_pb2.py
TimeFilterFastRequest_pb2.py
TimeFilterFastResponse_pb2.py
benchmarks/__init__.py
benchmarks/common.py
benchmarks/time_filter.py
benchmarks/time_filter_fast.py
benchmarks/time_map.py
examples/README.md
examples/geocoding.py
examples/requirements.txt
examples/time_filter.py
examples/time_filter_fast_matrix.py
examples/time_filter_fast_proto.py
examples/time_filter_matrix.py
proto/RequestsCommon.proto
proto/TimeFilterFastRequest.proto
proto/TimeFilterFastResponse.proto
scripts/generate_async_client.py
tests/__init__.py
tests/conftest.py
tests/distance_map_test.py
tests/errors_test.py
tests/geocoding_test.py
tests/geohash_fast_test.py
tests/geohash_test.py
tests/h3_fast_test.py
tests/h3_test.py
tests/map_info_test.py
tests/postcodes_test.py
tests/retry_test.py
tests/routes_test.py
tests/rpm_limits_test.py
tests/supported_locations_test.py
tests/time_filter_fast_test.py
tests/time_filter_proto_test.py
tests/time_filter_test.py
tests/time_map_fast_test.py
tests/time_map_test.py
tests/wkt_parsing_test.py
tests/wkt_pretty_print_test.py
tests/wkt_validate_objects_test.py
traveltimepy/__init__.py
traveltimepy/accept_type.py
traveltimepy/async_base_client.py
traveltimepy/async_client.py
traveltimepy/base_client.py
traveltimepy/client.py
traveltimepy/errors.py
traveltimepy/itertools.py
traveltimepy/py.typed
traveltimepy/sync_base_client.py
traveltimepy/requests/__init__.py
traveltimepy/requests/common.py
traveltimepy/requests/distance_map.py
traveltimepy/requests/geocoding.py
traveltimepy/requests/geohash.py
traveltimepy/requests/geohash_fast.py
traveltimepy/requests/h3.py
traveltimepy/requests/h3_fast.py
traveltimepy/requests/level_of_detail.py
traveltimepy/requests/postcodes.py
traveltimepy/requests/postcodes_zones.py
traveltimepy/requests/request.py
traveltimepy/requests/routes.py
traveltimepy/requests/supported_locations.py
traveltimepy/requests/time_filter.py
traveltimepy/requests/time_filter_fast.py
traveltimepy/requests/time_filter_proto.py
traveltimepy-4.2.2.dist-info/licenses/LICENSE
traveltimepy-4.2.2.dist-info/METADATA
traveltimepy-4.2.2.dist-info/WHEEL
traveltimepy-4.2.2.dist-info/top_level.txt
traveltimepy-4.2.2.dist-info/RECORD
