Metadata-Version: 2.4
Name: traveltimepy
Version: 4.2.2
Summary: Python Interface to Travel Time.
Author: TravelTime
License: MIT
Keywords: traveltimepy,api,maps
Classifier: Programming Language :: Python :: 3
Classifier: Programming Language :: Python :: 3.8
Classifier: Programming Language :: Python :: 3.9
Classifier: Programming Language :: Python :: 3.10
Classifier: Programming Language :: Python :: 3.11
Classifier: Programming Language :: Python :: 3.12
Classifier: License :: OSI Approved :: MIT License
Requires-Python: >=3.8
License-File: LICENSE
Requires-Dist: pydantic
Requires-Dist: typing-extensions
Requires-Dist: geojson-pydantic>=1.0.1
Requires-Dist: shapely
Requires-Dist: dacite
Requires-Dist: certifi>=2021.5.30
Requires-Dist: aiohttp
Requires-Dist: aiolimiter
Requires-Dist: tenacity
Requires-Dist: requests
Requires-Dist: requests-ratelimiter
Provides-Extra: proto
Requires-Dist: protobuf==4.25.8; extra == "proto"
Requires-Dist: types-protobuf; extra == "proto"
Provides-Extra: test
Requires-Dist: pytest; extra == "test"
Requires-Dist: pytest-asyncio; extra == "test"
Requires-Dist: flake8; extra == "test"
Requires-Dist: flake8-pyproject; extra == "test"
Requires-Dist: mypy; extra == "test"
Requires-Dist: black; extra == "test"
Requires-Dist: types-shapely; extra == "test"
Requires-Dist: docformatter; extra == "test"
Dynamic: license-file
